geeet/MOST.py
geeet/__init__.py
geeet/common.py
geeet/meteo.py
geeet/ptjpl.py
geeet/resistances.py
geeet/solar.py
geeet/tseb.py
geeet/vegetation.py
geeet/eepredefined/__init__.py
geeet/eepredefined/cmd_utils.py
geeet/eepredefined/join.py
geeet/eepredefined/landsat.py
geeet/eepredefined/masks.py
geeet/eepredefined/metprep.py
geeet/eepredefined/parsers.py
geeet/eepredefined/pixel_area.py
geeet/eepredefined/reducers.py
geeet/eepredefined/workflows.py
geeet-0.3.0.dist-info/LICENSE
geeet-0.3.0.dist-info/METADATA
geeet-0.3.0.dist-info/WHEEL
geeet-0.3.0.dist-info/dependency_links.txt
geeet-0.3.0.dist-info/entry_points.txt
geeet-0.3.0.dist-info/top_level.txt
geeet-0.3.0.dist-info/RECORD
