Metadata-Version: 2.1
Name: geeet
Version: 0.3.0
Summary: Evapotranspiration (ET) models for use in python and with integration into Google Earth Engine.
Home-page: https://github.com/lopezvoliver/geeet
Author: Oliver Lopez
Author-email: lopezv.oliver@gmail.com
License: MIT license
Keywords: geeet
Classifier: Intended Audience :: Developers
Classifier: License :: OSI Approved :: MIT License
Classifier: Natural Language :: English
Classifier: Programming Language :: Python :: 3
Classifier: Programming Language :: Python :: 3.7
Classifier: Programming Language :: Python :: 3.8
Classifier: Programming Language :: Python :: 3.9
Requires-Python: >=3.6
License-File: LICENSE
Requires-Dist: numpy
Provides-Extra: all
Requires-Dist: pip ; extra == 'all'
Requires-Dist: bump2version ; extra == 'all'
Requires-Dist: wheel ; extra == 'all'
Requires-Dist: watchdog ; extra == 'all'
Requires-Dist: flake8 ; extra == 'all'
Requires-Dist: tox ; extra == 'all'
Requires-Dist: coverage ; extra == 'all'
Requires-Dist: Sphinx ; extra == 'all'
Requires-Dist: twine ; extra == 'all'
Requires-Dist: grip ; extra == 'all'
Requires-Dist: xarray ; extra == 'all'
Requires-Dist: earthengine-api ; extra == 'all'
